unclick/__init__.py
unclick/core.py
unclick-0.1.0.dist-info/LICENSE.md
unclick-0.1.0.dist-info/METADATA
unclick-0.1.0.dist-info/WHEEL
unclick-0.1.0.dist-info/RECORD
