Metadata-Version: 2.1
Name: unclick
Version: 0.1.0
Summary: A reverse parser for the click CLI library
License: BSD 3-clause
Author: José Sánchez-Gallego
Author-email: gallegoj@uw.edu
Requires-Python: >=3.8,<4.0
Classifier: License :: Other/Proprietary License
Classifier: Programming Language :: Python :: 3
Classifier: Programming Language :: Python :: 3.8
Classifier: Programming Language :: Python :: 3.9
Classifier: Programming Language :: Python :: 3.10
Classifier: Programming Language :: Python :: 3.11
Classifier: Programming Language :: Python :: 3.12
Requires-Dist: click (>=8.0.0,<9.0.0)
Requires-Dist: makefun (>=1.15.1,<2.0.0)
